mosaik_api.py
example_mas/__init__.py
example_mas/mosaik.py
example_sim/__init__.py
example_sim/mosaik.py
example_sim/simulator.py
mosaik.API_SemVer-2.4.2rc20221110010448.dist-info/AUTHORS.txt
mosaik.API_SemVer-2.4.2rc20221110010448.dist-info/LICENSE.txt
mosaik.API_SemVer-2.4.2rc20221110010448.dist-info/METADATA
mosaik.API_SemVer-2.4.2rc20221110010448.dist-info/WHEEL
mosaik.API_SemVer-2.4.2rc20221110010448.dist-info/entry_points.txt
mosaik.API_SemVer-2.4.2rc20221110010448.dist-info/top_level.txt
mosaik.API_SemVer-2.4.2rc20221110010448.dist-info/RECORD
